{
  "SPY": {
    "price": 737.78,
    "change_pct": 1.7,
    "updated": "2026-06-11T19:28:09Z"
  },
  "QQQ": {
    "price": 715.2,
    "change_pct": -0.01,
    "updated": "2026-06-11T19:28:09Z"
  },
  "DIA": {
    "price": 509.46,
    "change_pct": 1.84,
    "updated": "2026-06-11T19:28:09Z"
  },
  "IWM": {
    "price": 290.1,
    "change_pct": 2.85,
    "updated": "2026-06-11T19:28:09Z"
  },
  "AMAT": {
    "price": 550.0,
    "change_pct": -0.15,
    "updated": "2026-06-11T19:28:09Z"
  },
  "AMD": {
    "price": 486.68,
    "change_pct": 0.11,
    "updated": "2026-06-11T19:28:09Z"
  },
  "AMGN": {
    "price": 357.83,
    "change_pct": -0.03,
    "updated": "2026-06-11T19:28:09Z"
  },
  "AMKR": {
    "price": 74.77,
    "change_pct": -0.2,
    "updated": "2026-06-11T19:28:09Z"
  },
  "ARM": {
    "price": 340.65,
    "change_pct": -13.39,
    "updated": "2026-06-11T19:28:09Z"
  },
  "ASYS": {
    "price": 22.04,
    "change_pct": -2.8,
    "updated": "2026-06-11T19:28:09Z"
  },
  "AVAXUSD": {
    "price": 6.62,
    "change_pct": 0.0,
    "updated": "2026-06-11T19:28:09Z"
  },
  "AXON": {
    "price": 442.79,
    "change_pct": -4.59,
    "updated": "2026-06-11T19:28:09Z"
  },
  "CAT": {
    "price": 896.07,
    "change_pct": -0.1,
    "updated": "2026-06-11T19:28:09Z"
  },
  "CLS": {
    "price": 384.94,
    "change_pct": -0.14,
    "updated": "2026-06-11T19:28:09Z"
  },
  "CMPS": {
    "price": 11.29,
    "change_pct": -20.17,
    "updated": "2026-06-11T19:28:09Z"
  },
  "CRWD": {
    "price": 692.64,
    "change_pct": -0.04,
    "updated": "2026-06-11T19:28:09Z"
  },
  "DELL": {
    "price": 391.34,
    "change_pct": -0.04,
    "updated": "2026-06-11T19:28:09Z"
  },
  "DKNG": {
    "price": 29.86,
    "change_pct": 0.01,
    "updated": "2026-06-11T19:28:09Z"
  },
  "FCX": {
    "price": 65.92,
    "change_pct": -0.03,
    "updated": "2026-06-11T19:28:09Z"
  },
  "FTNT": {
    "price": 145.93,
    "change_pct": -0.01,
    "updated": "2026-06-11T19:28:09Z"
  },
  "GE": {
    "price": 329.95,
    "change_pct": -0.0,
    "updated": "2026-06-11T19:28:09Z"
  },
  "HIMX": {
    "price": 17.46,
    "change_pct": -27.91,
    "updated": "2026-06-11T19:28:09Z"
  },
  "HOOD": {
    "price": 92.86,
    "change_pct": -0.1,
    "updated": "2026-06-11T19:28:09Z"
  },
  "INSG": {
    "price": 10.6,
    "change_pct": -26.87,
    "updated": "2026-06-11T19:28:09Z"
  },
  "INTC": {
    "price": 117.45,
    "change_pct": -0.09,
    "updated": "2026-06-11T19:28:09Z"
  },
  "KLAC": {
    "price": 2407.01,
    "change_pct": -0.05,
    "updated": "2026-06-11T19:28:09Z"
  },
  "LMT": {
    "price": 550.28,
    "change_pct": -0.0,
    "updated": "2026-06-11T19:28:09Z"
  },
  "LRCX": {
    "price": 360.98,
    "change_pct": 0.03,
    "updated": "2026-06-11T19:28:09Z"
  },
  "MRK": {
    "price": 122.15,
    "change_pct": -0.04,
    "updated": "2026-06-11T19:28:09Z"
  },
  "MRVL": {
    "price": 278.85,
    "change_pct": 0.03,
    "updated": "2026-06-11T19:28:09Z"
  },
  "MSFT": {
    "price": 387.49,
    "change_pct": -12.84,
    "updated": "2026-06-11T19:28:09Z"
  },
  "MU": {
    "price": 978.03,
    "change_pct": -0.03,
    "updated": "2026-06-11T19:28:09Z"
  },
  "NVTS": {
    "price": 21.82,
    "change_pct": -31.03,
    "updated": "2026-06-11T19:28:09Z"
  },
  "ORCL": {
    "price": 182.7,
    "change_pct": -25.51,
    "updated": "2026-06-11T19:28:09Z"
  },
  "PANW": {
    "price": 277.64,
    "change_pct": -0.03,
    "updated": "2026-06-11T19:28:09Z"
  },
  "PENG": {
    "price": 63.09,
    "change_pct": -11.29,
    "updated": "2026-06-11T19:28:09Z"
  },
  "RIOT": {
    "price": 26.13,
    "change_pct": 0.15,
    "updated": "2026-06-11T19:28:09Z"
  },
  "RTX": {
    "price": 183.72,
    "change_pct": -0.04,
    "updated": "2026-06-11T19:28:09Z"
  },
  "SHW": {
    "price": 314.85,
    "change_pct": -0.01,
    "updated": "2026-06-11T19:28:09Z"
  },
  "SPCE": {
    "price": 6.03,
    "change_pct": -15.19,
    "updated": "2026-06-11T19:28:09Z"
  },
  "STX": {
    "price": 863.32,
    "change_pct": -8.13,
    "updated": "2026-06-11T19:28:09Z"
  },
  "TER": {
    "price": 376.02,
    "change_pct": -0.08,
    "updated": "2026-06-11T19:28:09Z"
  },
  "TXN": {
    "price": 297.41,
    "change_pct": -0.08,
    "updated": "2026-06-11T19:28:09Z"
  },
  "XLB": {
    "price": 51.13,
    "change_pct": 0.0,
    "updated": "2026-06-11T19:28:09Z"
  },
  "XLK": {
    "price": 182.62,
    "change_pct": -0.01,
    "updated": "2026-06-11T19:28:09Z"
  },
  "ELVN": {
    "price": 41.43,
    "change_pct": 0.0,
    "updated": "2026-06-11T19:28:09Z"
  },
  "SFIX": {
    "price": 4.2,
    "change_pct": 0.0,
    "updated": "2026-06-11T19:28:09Z"
  },
  "TEO": {
    "price": 16.16,
    "change_pct": 0.0,
    "updated": "2026-06-11T19:28:09Z"
  },
  "ADPT": {
    "price": 18.82,
    "change_pct": 0.0,
    "updated": "2026-06-11T19:28:09Z"
  },
  "BBAR": {
    "price": 20.22,
    "change_pct": 0.0,
    "updated": "2026-06-11T19:28:09Z"
  },
  "ATEX": {
    "price": 80.3,
    "change_pct": 0.0,
    "updated": "2026-06-11T19:28:09Z"
  },
  "BMA": {
    "price": 98.58,
    "change_pct": 0.0,
    "updated": "2026-06-11T19:28:09Z"
  },
  "ASTI": {
    "price": 8.97,
    "change_pct": 0.0,
    "updated": "2026-06-11T19:28:09Z"
  },
  "GGAL": {
    "price": 55.54,
    "change_pct": 0.0,
    "updated": "2026-06-11T19:28:09Z"
  },
  "ENTG": {
    "price": 144.1,
    "change_pct": 0.0,
    "updated": "2026-06-11T19:28:09Z"
  },
  "BROS": {
    "price": 64.16,
    "change_pct": 0.0,
    "updated": "2026-06-11T19:28:09Z"
  },
  "SPIR": {
    "price": 19.43,
    "change_pct": 0.0,
    "updated": "2026-06-11T19:28:09Z"
  },
  "ALAB": {
    "price": 358.64,
    "change_pct": 0.0,
    "updated": "2026-06-11T19:28:09Z"
  },
  "YSS": {
    "price": 33.15,
    "change_pct": 0.0,
    "updated": "2026-06-11T19:28:09Z"
  },
  "CPNG": {
    "price": 17.03,
    "change_pct": 0.0,
    "updated": "2026-06-11T19:28:09Z"
  },
  "TNA": {
    "price": 67.6,
    "change_pct": 0.0,
    "updated": "2026-06-11T19:28:09Z"
  },
  "UCTT": {
    "price": 103.14,
    "change_pct": 0.0,
    "updated": "2026-06-11T19:28:09Z"
  },
  "CRDO": {
    "price": 261.98,
    "change_pct": 0.0,
    "updated": "2026-06-11T19:28:09Z"
  },
  "PLAY": {
    "price": 13.18,
    "change_pct": 0.0,
    "updated": "2026-06-11T19:28:09Z"
  },
  "ICHR": {
    "price": 80.98,
    "change_pct": 0.0,
    "updated": "2026-06-11T19:28:09Z"
  },
  "FUBO": {
    "price": 10.48,
    "change_pct": 0.0,
    "updated": "2026-06-11T19:28:09Z"
  },
  "OI": {
    "price": 8.87,
    "change_pct": 0.0,
    "updated": "2026-06-11T19:28:09Z"
  },
  "DNUT": {
    "price": 4.18,
    "change_pct": 0.0,
    "updated": "2026-06-11T19:28:09Z"
  },
  "AEO": {
    "price": 18.14,
    "change_pct": 0.0,
    "updated": "2026-06-11T19:28:09Z"
  },
  "ATRO": {
    "price": 93.95,
    "change_pct": 0.0,
    "updated": "2026-06-11T19:28:09Z"
  },
  "COHU": {
    "price": 57.76,
    "change_pct": 0.0,
    "updated": "2026-06-11T19:28:09Z"
  },
  "AMC": {
    "price": 2.24,
    "change_pct": 0.0,
    "updated": "2026-06-11T19:28:09Z"
  },
  "BTGO": {
    "price": 5.44,
    "change_pct": 0.0,
    "updated": "2026-06-11T19:28:09Z"
  },
  "AMRX": {
    "price": 16.15,
    "change_pct": 0.0,
    "updated": "2026-06-11T19:28:09Z"
  },
  "ACMR": {
    "price": 89.53,
    "change_pct": 0.0,
    "updated": "2026-06-11T19:28:09Z"
  },
  "REAL": {
    "price": 9.72,
    "change_pct": 0.0,
    "updated": "2026-06-11T19:28:09Z"
  },
  "SNDK": {
    "price": 1866.3,
    "change_pct": 0.0,
    "updated": "2026-06-11T19:28:09Z"
  },
  "BLMN": {
    "price": 7.89,
    "change_pct": 0.0,
    "updated": "2026-06-11T19:28:09Z"
  },
  "TTMI": {
    "price": 183.3,
    "change_pct": 0.0,
    "updated": "2026-06-11T19:28:09Z"
  },
  "ASX": {
    "price": 36.81,
    "change_pct": 0.0,
    "updated": "2026-06-11T19:28:09Z"
  },
  "KSS": {
    "price": 17.33,
    "change_pct": 0.0,
    "updated": "2026-06-11T19:28:09Z"
  },
  "VOYG": {
    "price": 47.86,
    "change_pct": 0.0,
    "updated": "2026-06-11T19:28:09Z"
  },
  "FLY": {
    "price": 38.99,
    "change_pct": 0.0,
    "updated": "2026-06-11T19:28:09Z"
  },
  "ASTS": {
    "price": 97.48,
    "change_pct": 0.0,
    "updated": "2026-06-11T19:28:09Z"
  },
  "DGXX": {
    "price": 6.36,
    "change_pct": 0.0,
    "updated": "2026-06-11T19:28:09Z"
  },
  "AI": {
    "price": 11.21,
    "change_pct": 0.0,
    "updated": "2026-06-11T19:28:09Z"
  },
  "XRX": {
    "price": 3.42,
    "change_pct": 0.0,
    "updated": "2026-06-11T19:28:09Z"
  },
  "COIN": {
    "price": 160.41,
    "change_pct": 0.0,
    "updated": "2026-06-11T19:28:09Z"
  },
  "CRBG": {
    "price": 28.08,
    "change_pct": 0.0,
    "updated": "2026-06-11T19:28:09Z"
  },
  "EWT": {
    "price": 102.38,
    "change_pct": 0.0,
    "updated": "2026-06-11T19:28:09Z"
  },
  "LUNR": {
    "price": 30.63,
    "change_pct": 0.0,
    "updated": "2026-06-11T19:28:09Z"
  },
  "SBUX": {
    "price": 102.29,
    "change_pct": 0.0,
    "updated": "2026-06-11T19:28:09Z"
  },
  "IREN": {
    "price": 56.51,
    "change_pct": 0.0,
    "updated": "2026-06-11T19:28:09Z"
  },
  "VSAT": {
    "price": 71.46,
    "change_pct": 0.0,
    "updated": "2026-06-11T19:28:09Z"
  },
  "AAL": {
    "price": 14.22,
    "change_pct": 0.0,
    "updated": "2026-06-11T19:28:09Z"
  },
  "PL": {
    "price": 33.81,
    "change_pct": 0.0,
    "updated": "2026-06-11T19:28:09Z"
  },
  "ALK": {
    "price": 45.61,
    "change_pct": 0.0,
    "updated": "2026-06-11T19:28:09Z"
  },
  "CRCL": {
    "price": 82.62,
    "change_pct": 0.0,
    "updated": "2026-06-11T19:28:09Z"
  },
  "NLY": {
    "price": 22.07,
    "change_pct": 0.0,
    "updated": "2026-06-11T19:28:09Z"
  },
  "DDD": {
    "price": 3.05,
    "change_pct": 0.0,
    "updated": "2026-06-11T19:28:09Z"
  },
  "MNRO": {
    "price": 15.64,
    "change_pct": 0.0,
    "updated": "2026-06-11T19:28:09Z"
  },
  "TROX": {
    "price": 7.73,
    "change_pct": 0.0,
    "updated": "2026-06-11T19:28:09Z"
  },
  "APH": {
    "price": 151.82,
    "change_pct": 0.0,
    "updated": "2026-06-11T19:28:09Z"
  },
  "GENI": {
    "price": 6.95,
    "change_pct": 0.0,
    "updated": "2026-06-11T19:28:09Z"
  },
  "LYG": {
    "price": 5.36,
    "change_pct": 0.0,
    "updated": "2026-06-11T19:28:09Z"
  },
  "ELAN": {
    "price": 23.92,
    "change_pct": 0.0,
    "updated": "2026-06-11T19:28:09Z"
  },
  "TSLA": {
    "price": 396.01,
    "change_pct": 0.0,
    "updated": "2026-06-11T19:28:09Z"
  },
  "RGTI": {
    "price": 20.84,
    "change_pct": 0.0,
    "updated": "2026-06-11T19:28:09Z"
  },
  "CCL": {
    "price": 27.48,
    "change_pct": 0.0,
    "updated": "2026-06-11T19:28:09Z"
  },
  "WDC": {
    "price": 519.4,
    "change_pct": 0.0,
    "updated": "2026-06-11T19:28:09Z"
  },
  "CIFR": {
    "price": 22.56,
    "change_pct": 0.0,
    "updated": "2026-06-11T19:28:09Z"
  },
  "HON": {
    "price": 217.99,
    "change_pct": 0.0,
    "updated": "2026-06-11T19:28:09Z"
  },
  "BA": {
    "price": 219.83,
    "change_pct": 0.0,
    "updated": "2026-06-11T19:28:09Z"
  },
  "ALB": {
    "price": 158.78,
    "change_pct": 0.0,
    "updated": "2026-06-11T19:28:09Z"
  },
  "BKSY": {
    "price": 34.96,
    "change_pct": 0.0,
    "updated": "2026-06-11T19:28:09Z"
  },
  "SAN": {
    "price": 12.48,
    "change_pct": 0.0,
    "updated": "2026-06-11T19:28:09Z"
  }
}