{
  "SPY": {
    "price": 754.76,
    "change_pct": -0.63,
    "updated": "2026-06-03T19:26:12Z"
  },
  "QQQ": {
    "price": 744.04,
    "change_pct": -0.28,
    "updated": "2026-06-03T19:26:12Z"
  },
  "DIA": {
    "price": 508.88,
    "change_pct": -1.01,
    "updated": "2026-06-03T19:26:12Z"
  },
  "IWM": {
    "price": 287.12,
    "change_pct": -1.56,
    "updated": "2026-06-03T19:26:12Z"
  },
  "AAVEUSD": {
    "price": 75.03,
    "change_pct": -0.67,
    "updated": "2026-06-03T19:26:12Z"
  },
  "AMKR": {
    "price": 75.52,
    "change_pct": -2.44,
    "updated": "2026-06-03T19:26:12Z"
  },
  "ARM": {
    "price": 410.91,
    "change_pct": 4.47,
    "updated": "2026-06-03T19:26:12Z"
  },
  "ASYS": {
    "price": 21.24,
    "change_pct": -6.29,
    "updated": "2026-06-03T19:26:12Z"
  },
  "AVAXUSD": {
    "price": 8.12,
    "change_pct": 0.0,
    "updated": "2026-06-03T19:26:12Z"
  },
  "AXON": {
    "price": 476.75,
    "change_pct": 2.73,
    "updated": "2026-06-03T19:26:12Z"
  },
  "BBY": {
    "price": 71.34,
    "change_pct": -4.39,
    "updated": "2026-06-03T19:26:12Z"
  },
  "BTCUSD": {
    "price": 65695.35,
    "change_pct": -7.32,
    "updated": "2026-06-03T19:26:12Z"
  },
  "CMPS": {
    "price": 12.82,
    "change_pct": -9.23,
    "updated": "2026-06-03T19:26:12Z"
  },
  "CRM": {
    "price": 190.78,
    "change_pct": -4.12,
    "updated": "2026-06-03T19:26:12Z"
  },
  "DKNG": {
    "price": 24.99,
    "change_pct": -1.59,
    "updated": "2026-06-03T19:26:12Z"
  },
  "DOGEUSD": {
    "price": 0.09,
    "change_pct": -7.84,
    "updated": "2026-06-03T19:26:12Z"
  },
  "DOTUSD": {
    "price": 1.11,
    "change_pct": 0.0,
    "updated": "2026-06-03T19:26:12Z"
  },
  "ETHUSD": {
    "price": 1813.31,
    "change_pct": -9.03,
    "updated": "2026-06-03T19:26:12Z"
  },
  "GENI": {
    "price": 5.86,
    "change_pct": -1.17,
    "updated": "2026-06-03T19:26:12Z"
  },
  "HIMX": {
    "price": 23.95,
    "change_pct": -1.03,
    "updated": "2026-06-03T19:26:12Z"
  },
  "INSG": {
    "price": 13.73,
    "change_pct": -5.26,
    "updated": "2026-06-03T19:26:12Z"
  },
  "LINKUSD": {
    "price": 8.3,
    "change_pct": -8.02,
    "updated": "2026-06-03T19:26:12Z"
  },
  "LTCUSD": {
    "price": 47.65,
    "change_pct": 0.0,
    "updated": "2026-06-03T19:26:12Z"
  },
  "MSFT": {
    "price": 427.8,
    "change_pct": -3.83,
    "updated": "2026-06-03T19:26:12Z"
  },
  "NVTS": {
    "price": 30.45,
    "change_pct": -2.25,
    "updated": "2026-06-03T19:26:12Z"
  },
  "ORCL": {
    "price": 231.32,
    "change_pct": -5.68,
    "updated": "2026-06-03T19:26:12Z"
  },
  "PENG": {
    "price": 71.45,
    "change_pct": 0.44,
    "updated": "2026-06-03T19:26:12Z"
  },
  "PLTR": {
    "price": 141.56,
    "change_pct": -7.63,
    "updated": "2026-06-03T19:26:12Z"
  },
  "PRAX": {
    "price": 272.31,
    "change_pct": -0.11,
    "updated": "2026-06-03T19:26:12Z"
  },
  "SOLUSD": {
    "price": 72.29,
    "change_pct": -10.33,
    "updated": "2026-06-03T19:26:12Z"
  },
  "SPCE": {
    "price": 4.24,
    "change_pct": -40.37,
    "updated": "2026-06-03T19:26:12Z"
  },
  "STX": {
    "price": 939.7,
    "change_pct": -0.01,
    "updated": "2026-06-03T19:26:12Z"
  },
  "TMHC": {
    "price": 71.53,
    "change_pct": 0.02,
    "updated": "2026-06-03T19:26:12Z"
  },
  "UNIUSD": {
    "price": 2.84,
    "change_pct": -4.5,
    "updated": "2026-06-03T19:26:12Z"
  },
  "XRPUSD": {
    "price": 1.21,
    "change_pct": -1.16,
    "updated": "2026-06-03T19:26:12Z"
  },
  "VGNT": {
    "price": 49.12,
    "change_pct": 0.0,
    "updated": "2026-06-03T19:26:12Z"
  },
  "MEI": {
    "price": 13.36,
    "change_pct": 0.0,
    "updated": "2026-06-03T19:26:12Z"
  },
  "MMED": {
    "price": 14.28,
    "change_pct": 0.0,
    "updated": "2026-06-03T19:26:12Z"
  },
  "TLYS": {
    "price": 4.75,
    "change_pct": 0.0,
    "updated": "2026-06-03T19:26:12Z"
  },
  "GME": {
    "price": 22.45,
    "change_pct": 0.0,
    "updated": "2026-06-03T19:26:12Z"
  },
  "CDNL": {
    "price": 61.19,
    "change_pct": 0.0,
    "updated": "2026-06-03T19:26:12Z"
  },
  "SNDK": {
    "price": 1824.3,
    "change_pct": 0.0,
    "updated": "2026-06-03T19:26:12Z"
  },
  "BTDR": {
    "price": 20.04,
    "change_pct": 0.0,
    "updated": "2026-06-03T19:26:12Z"
  },
  "MX": {
    "price": 8.84,
    "change_pct": 0.0,
    "updated": "2026-06-03T19:26:12Z"
  },
  "BRKR": {
    "price": 61.45,
    "change_pct": 0.0,
    "updated": "2026-06-03T19:26:12Z"
  },
  "RIVN": {
    "price": 18.01,
    "change_pct": 0.0,
    "updated": "2026-06-03T19:26:12Z"
  },
  "APTV": {
    "price": 77.66,
    "change_pct": 0.0,
    "updated": "2026-06-03T19:26:12Z"
  },
  "QURE": {
    "price": 29.59,
    "change_pct": 0.0,
    "updated": "2026-06-03T19:26:12Z"
  },
  "POET": {
    "price": 14.94,
    "change_pct": 0.0,
    "updated": "2026-06-03T19:26:12Z"
  },
  "MRVL": {
    "price": 302.07,
    "change_pct": 0.0,
    "updated": "2026-06-03T19:26:12Z"
  },
  "WDC": {
    "price": 591.14,
    "change_pct": 0.0,
    "updated": "2026-06-03T19:26:12Z"
  },
  "ACHC": {
    "price": 25.97,
    "change_pct": 0.0,
    "updated": "2026-06-03T19:26:12Z"
  },
  "STRL": {
    "price": 958.27,
    "change_pct": 0.0,
    "updated": "2026-06-03T19:26:12Z"
  },
  "TGTX": {
    "price": 39.92,
    "change_pct": 0.0,
    "updated": "2026-06-03T19:26:12Z"
  },
  "REPL": {
    "price": 9.83,
    "change_pct": 0.0,
    "updated": "2026-06-03T19:26:12Z"
  },
  "MRX": {
    "price": 54.56,
    "change_pct": 0.0,
    "updated": "2026-06-03T19:26:12Z"
  },
  "URI": {
    "price": 1058.86,
    "change_pct": 0.0,
    "updated": "2026-06-03T19:26:12Z"
  },
  "PCT": {
    "price": 13.73,
    "change_pct": 0.0,
    "updated": "2026-06-03T19:26:12Z"
  },
  "APGE": {
    "price": 83.86,
    "change_pct": 0.0,
    "updated": "2026-06-03T19:26:12Z"
  },
  "KMX": {
    "price": 46.54,
    "change_pct": 0.0,
    "updated": "2026-06-03T19:26:12Z"
  },
  "BHVN": {
    "price": 10.59,
    "change_pct": 0.0,
    "updated": "2026-06-03T19:26:12Z"
  },
  "SVV": {
    "price": 9.5,
    "change_pct": 0.0,
    "updated": "2026-06-03T19:26:12Z"
  },
  "FRVO": {
    "price": 40.01,
    "change_pct": 0.0,
    "updated": "2026-06-03T19:26:12Z"
  },
  "ADI": {
    "price": 437.52,
    "change_pct": 0.0,
    "updated": "2026-06-03T19:26:12Z"
  },
  "AMD": {
    "price": 537.52,
    "change_pct": 0.0,
    "updated": "2026-06-03T19:26:12Z"
  },
  "FAST": {
    "price": 46.33,
    "change_pct": 0.0,
    "updated": "2026-06-03T19:26:12Z"
  },
  "NBIX": {
    "price": 165.29,
    "change_pct": 0.0,
    "updated": "2026-06-03T19:26:12Z"
  },
  "WTI": {
    "price": 4.07,
    "change_pct": 0.0,
    "updated": "2026-06-03T19:26:12Z"
  },
  "DE": {
    "price": 588.45,
    "change_pct": 0.0,
    "updated": "2026-06-03T19:26:12Z"
  },
  "AMAT": {
    "price": 499.14,
    "change_pct": 0.0,
    "updated": "2026-06-03T19:26:12Z"
  },
  "LESL": {
    "price": 4.49,
    "change_pct": 0.0,
    "updated": "2026-06-03T19:26:12Z"
  },
  "MRNA": {
    "price": 48.72,
    "change_pct": 0.0,
    "updated": "2026-06-03T19:26:12Z"
  },
  "MDT": {
    "price": 77.69,
    "change_pct": 0.0,
    "updated": "2026-06-03T19:26:12Z"
  },
  "TTMI": {
    "price": 188.06,
    "change_pct": 0.0,
    "updated": "2026-06-03T19:26:12Z"
  },
  "TBN": {
    "price": 34.96,
    "change_pct": 0.0,
    "updated": "2026-06-03T19:26:12Z"
  },
  "INCY": {
    "price": 98.02,
    "change_pct": 0.0,
    "updated": "2026-06-03T19:26:12Z"
  },
  "META": {
    "price": 620.91,
    "change_pct": 0.0,
    "updated": "2026-06-03T19:26:12Z"
  },
  "WMT": {
    "price": 116.85,
    "change_pct": 0.0,
    "updated": "2026-06-03T19:26:12Z"
  },
  "NN": {
    "price": 21.65,
    "change_pct": 0.0,
    "updated": "2026-06-03T19:26:12Z"
  },
  "EXEL": {
    "price": 51.43,
    "change_pct": 0.0,
    "updated": "2026-06-03T19:26:12Z"
  },
  "CIEN": {
    "price": 627.45,
    "change_pct": 0.0,
    "updated": "2026-06-03T19:26:12Z"
  },
  "AVGO": {
    "price": 485.83,
    "change_pct": 0.0,
    "updated": "2026-06-03T19:26:12Z"
  },
  "STM": {
    "price": 80.05,
    "change_pct": 0.0,
    "updated": "2026-06-03T19:26:12Z"
  },
  "KOS": {
    "price": 2.99,
    "change_pct": 0.0,
    "updated": "2026-06-03T19:26:12Z"
  },
  "MU": {
    "price": 1071.01,
    "change_pct": 0.0,
    "updated": "2026-06-03T19:26:12Z"
  },
  "CSCO": {
    "price": 129.12,
    "change_pct": 0.0,
    "updated": "2026-06-03T19:26:12Z"
  },
  "XLE": {
    "price": 58.9,
    "change_pct": 0.0,
    "updated": "2026-06-03T19:26:12Z"
  },
  "XOM": {
    "price": 153.45,
    "change_pct": 0.0,
    "updated": "2026-06-03T19:26:12Z"
  },
  "COP": {
    "price": 119.04,
    "change_pct": 0.0,
    "updated": "2026-06-03T19:26:12Z"
  },
  "CVE": {
    "price": 29.6,
    "change_pct": 0.0,
    "updated": "2026-06-03T19:26:12Z"
  },
  "TPL": {
    "price": 406.99,
    "change_pct": 0.0,
    "updated": "2026-06-03T19:26:12Z"
  },
  "CAT": {
    "price": 925.75,
    "change_pct": 0.0,
    "updated": "2026-06-03T19:26:12Z"
  },
  "OXY": {
    "price": 59.92,
    "change_pct": 0.0,
    "updated": "2026-06-03T19:26:12Z"
  },
  "NOK": {
    "price": 16.8,
    "change_pct": 0.0,
    "updated": "2026-06-03T19:26:12Z"
  },
  "REGN": {
    "price": 621.61,
    "change_pct": 0.0,
    "updated": "2026-06-03T19:26:12Z"
  },
  "NET": {
    "price": 266.86,
    "change_pct": 0.0,
    "updated": "2026-06-03T19:26:12Z"
  },
  "HPE": {
    "price": 55.17,
    "change_pct": 0.0,
    "updated": "2026-06-03T19:26:12Z"
  },
  "FCX": {
    "price": 71.33,
    "change_pct": 0.0,
    "updated": "2026-06-03T19:26:12Z"
  },
  "KEEL": {
    "price": 6.11,
    "change_pct": 0.0,
    "updated": "2026-06-03T19:26:12Z"
  },
  "CRWD": {
    "price": 756.7,
    "change_pct": 0.0,
    "updated": "2026-06-03T19:26:12Z"
  },
  "UPB": {
    "price": 7.69,
    "change_pct": 0.0,
    "updated": "2026-06-03T19:26:12Z"
  },
  "MDGL": {
    "price": 480.97,
    "change_pct": 0.0,
    "updated": "2026-06-03T19:26:12Z"
  },
  "GENB": {
    "price": 12.72,
    "change_pct": 0.0,
    "updated": "2026-06-03T19:26:12Z"
  },
  "INTC": {
    "price": 111.65,
    "change_pct": 0.0,
    "updated": "2026-06-03T19:26:12Z"
  },
  "DOW": {
    "price": 35.47,
    "change_pct": 0.0,
    "updated": "2026-06-03T19:26:12Z"
  },
  "FSLR": {
    "price": 317.33,
    "change_pct": 0.0,
    "updated": "2026-06-03T19:26:12Z"
  },
  "SOLV": {
    "price": 78.45,
    "change_pct": 0.0,
    "updated": "2026-06-03T19:26:12Z"
  },
  "HST": {
    "price": 23.93,
    "change_pct": 0.0,
    "updated": "2026-06-03T19:26:12Z"
  },
  "CNQ": {
    "price": 47.78,
    "change_pct": 0.0,
    "updated": "2026-06-03T19:26:12Z"
  },
  "KEYS": {
    "price": 351.66,
    "change_pct": 0.0,
    "updated": "2026-06-03T19:26:12Z"
  },
  "VG": {
    "price": 12.68,
    "change_pct": 0.0,
    "updated": "2026-06-03T19:26:12Z"
  },
  "AMGN": {
    "price": 337.8,
    "change_pct": 0.0,
    "updated": "2026-06-03T19:26:12Z"
  },
  "CVX": {
    "price": 189.96,
    "change_pct": 0.0,
    "updated": "2026-06-03T19:26:12Z"
  },
  "EQIX": {
    "price": 1081.28,
    "change_pct": 0.0,
    "updated": "2026-06-03T19:26:12Z"
  },
  "ETN": {
    "price": 420.59,
    "change_pct": 0.0,
    "updated": "2026-06-03T19:26:12Z"
  },
  "ACI": {
    "price": 15.84,
    "change_pct": 0.0,
    "updated": "2026-06-03T19:26:12Z"
  },
  "SHW": {
    "price": 296.83,
    "change_pct": 0.0,
    "updated": "2026-06-03T19:26:12Z"
  },
  "TJX": {
    "price": 157.51,
    "change_pct": 0.0,
    "updated": "2026-06-03T19:26:12Z"
  },
  "GS": {
    "price": 1046.89,
    "change_pct": 0.0,
    "updated": "2026-06-03T19:26:12Z"
  },
  "ABVX": {
    "price": 88.94,
    "change_pct": 0.0,
    "updated": "2026-06-03T19:26:12Z"
  },
  "TSM": {
    "price": 439.6,
    "change_pct": 0.0,
    "updated": "2026-06-03T19:26:12Z"
  },
  "MS": {
    "price": 211.28,
    "change_pct": 0.0,
    "updated": "2026-06-03T19:26:12Z"
  },
  "BB": {
    "price": 9.97,
    "change_pct": 0.0,
    "updated": "2026-06-03T19:26:12Z"
  },
  "NAT": {
    "price": 5.21,
    "change_pct": 0.0,
    "updated": "2026-06-03T19:26:12Z"
  },
  "XLK": {
    "price": 196.35,
    "change_pct": 0.0,
    "updated": "2026-06-03T19:26:12Z"
  },
  "LIN": {
    "price": 507.83,
    "change_pct": 0.0,
    "updated": "2026-06-03T19:26:12Z"
  }
}