{
  "SPY": {
    "price": 759.57,
    "change_pct": 0.14,
    "updated": "2026-06-02T23:35:48Z"
  },
  "QQQ": {
    "price": 746.16,
    "change_pct": 0.46,
    "updated": "2026-06-02T23:35:48Z"
  },
  "DIA": {
    "price": 514.05,
    "change_pct": 0.51,
    "updated": "2026-06-02T23:35:48Z"
  },
  "IWM": {
    "price": 291.66,
    "change_pct": 0.93,
    "updated": "2026-06-02T23:35:48Z"
  },
  "ARM": {
    "price": 395.46,
    "change_pct": 0.54,
    "updated": "2026-06-02T23:35:48Z"
  },
  "ASYS": {
    "price": 21.0,
    "change_pct": -5.71,
    "updated": "2026-06-02T23:35:48Z"
  },
  "AVAXUSD": {
    "price": 8.06,
    "change_pct": 0.0,
    "updated": "2026-06-02T23:35:48Z"
  },
  "AXON": {
    "price": 489.05,
    "change_pct": 5.33,
    "updated": "2026-06-02T23:35:48Z"
  },
  "BBY": {
    "price": 72.85,
    "change_pct": -2.46,
    "updated": "2026-06-02T23:35:48Z"
  },
  "BTCUSD": {
    "price": 66409.5,
    "change_pct": -6.31,
    "updated": "2026-06-02T23:35:48Z"
  },
  "CMPS": {
    "price": 13.57,
    "change_pct": -4.07,
    "updated": "2026-06-02T23:35:48Z"
  },
  "CRM": {
    "price": 198.05,
    "change_pct": -0.2,
    "updated": "2026-06-02T23:35:48Z"
  },
  "DKNG": {
    "price": 25.23,
    "change_pct": -0.76,
    "updated": "2026-06-02T23:35:48Z"
  },
  "DOGEUSD": {
    "price": 0.09,
    "change_pct": -9.01,
    "updated": "2026-06-02T23:35:48Z"
  },
  "DOTUSD": {
    "price": 1.06,
    "change_pct": 0.0,
    "updated": "2026-06-02T23:35:48Z"
  },
  "ETHUSD": {
    "price": 1845.3,
    "change_pct": -7.43,
    "updated": "2026-06-02T23:35:48Z"
  },
  "GENI": {
    "price": 6.0,
    "change_pct": 1.21,
    "updated": "2026-06-02T23:35:48Z"
  },
  "HIMX": {
    "price": 23.99,
    "change_pct": -0.17,
    "updated": "2026-06-02T23:35:48Z"
  },
  "INSG": {
    "price": 14.45,
    "change_pct": 0.56,
    "updated": "2026-06-02T23:35:48Z"
  },
  "LINKUSD": {
    "price": 8.3,
    "change_pct": -8.06,
    "updated": "2026-06-02T23:35:48Z"
  },
  "LTCUSD": {
    "price": 46.45,
    "change_pct": 0.0,
    "updated": "2026-06-02T23:35:48Z"
  },
  "MSFT": {
    "price": 438.0,
    "change_pct": -1.35,
    "updated": "2026-06-02T23:35:48Z"
  },
  "ORCL": {
    "price": 237.5,
    "change_pct": -3.16,
    "updated": "2026-06-02T23:35:48Z"
  },
  "PENG": {
    "price": 70.3,
    "change_pct": -0.93,
    "updated": "2026-06-02T23:35:48Z"
  },
  "PLTR": {
    "price": 149.6,
    "change_pct": -2.23,
    "updated": "2026-06-02T23:35:48Z"
  },
  "SOLUSD": {
    "price": 72.91,
    "change_pct": -9.57,
    "updated": "2026-06-02T23:35:48Z"
  },
  "SPCE": {
    "price": 4.64,
    "change_pct": -34.74,
    "updated": "2026-06-02T23:35:48Z"
  },
  "STX": {
    "price": 923.08,
    "change_pct": -1.0,
    "updated": "2026-06-02T23:35:48Z"
  },
  "TMHC": {
    "price": 71.4,
    "change_pct": -0.16,
    "updated": "2026-06-02T23:35:48Z"
  },
  "UNIUSD": {
    "price": 2.74,
    "change_pct": -8.02,
    "updated": "2026-06-02T23:35:48Z"
  }
}